Metadata-Version: 2.1
Name: pypijsonip
Version: 0.8
Summary: test pypi network traffic
Author-email: Example author <Author@example.com>
